zcommon/__init__.py
zcommon/classes.py
zcommon/classes_test.py
zcommon/collections.py
zcommon/collections_test.py
zcommon/fs.py
zcommon/fs_test.py
zcommon/modules.py
zcommon/modules_test.py
zcommon/parsers.py
zcommon/schedule.py
zcommon/serialization.py
zcommon/shell.py
zcommon/textops.py
zcommon/textops_test.py
zcommon-0.1.2.dist-info/METADATA
zcommon-0.1.2.dist-info/WHEEL
zcommon-0.1.2.dist-info/top_level.txt
zcommon-0.1.2.dist-info/RECORD
